setup.py
contenttransformer/__init__.py
contenttransformer/app.py
contenttransformer/factory.py
contenttransformer/transformers.py
contenttransformer/utils.py
contenttransformer/web.py
contenttransformer.egg-info/PKG-INFO
contenttransformer.egg-info/SOURCES.txt
contenttransformer.egg-info/dependency_links.txt
contenttransformer.egg-info/entry_points.txt
contenttransformer.egg-info/not-zip-safe
contenttransformer.egg-info/requires.txt
contenttransformer.egg-info/top_level.txt