Metadata-Version: 1.0
Name: contenttransformer
Version: 0.3.3
Summary: transform e.g. file data based on type to be served TTW
Home-page: http://k0s.org/hg/contenttransformer
Author: Jeff Hammel
Author-email: k0scist@gmail.com
License: GPL
Platform: UNKNOWN
